{
  "category": "atexit",
  "entries": [
    {
      "key": "atexit.register",
      "abstract": "",
      "serializedNode": {
        "type": "PYTHON_CALL_MEMBER",
        "properties": {
          "member": "register"
        },
        "childSets": {
          "object": [
            {
              "type": "PY_IDENTIFIER",
              "properties": {
                "identifier": "atexit"
              },
              "childSets": {}
            }
          ],
          "arguments": [
            {
              "type": "PY_ARG",
              "childSets": {
                "argument": [
                  {
                    "type": "PYTHON_EXPRESSION",
                    "properties": {},
                    "childSets": {
                      "tokens": []
                    }
                  }
                ]
              },
              "properties": {}
            }
          ]
        }
      }
    },
    {
      "key": "atexit.unregister",
      "abstract": "",
      "serializedNode": {
        "type": "PYTHON_CALL_MEMBER",
        "properties": {
          "member": "unregister"
        },
        "childSets": {
          "object": [
            {
              "type": "PY_IDENTIFIER",
              "properties": {
                "identifier": "atexit"
              },
              "childSets": {}
            }
          ],
          "arguments": [
            {
              "type": "PY_ARG",
              "childSets": {
                "argument": [
                  {
                    "type": "PYTHON_EXPRESSION",
                    "properties": {},
                    "childSets": {
                      "tokens": []
                    }
                  }
                ]
              },
              "properties": {}
            }
          ]
        }
      }
    }
  ]
}