{
  "category": "compileall",
  "entries": [
    {
      "key": "compileall.PycInvalidationMode",
      "abstract": "",
      "serializedNode": {
        "type": "PYTHON_CALL_MEMBER",
        "properties": {
          "member": "PycInvalidationMode"
        },
        "childSets": {
          "object": [
            {
              "type": "PY_IDENTIFIER",
              "properties": {
                "identifier": "compileall"
              },
              "childSets": {}
            }
          ],
          "arguments": [
            {
              "type": "PY_ARG",
              "childSets": {
                "argument": [
                  {
                    "type": "PYTHON_EXPRESSION",
                    "properties": {},
                    "childSets": {
                      "tokens": []
                    }
                  }
                ]
              },
              "properties": {}
            }
          ]
        }
      }
    },
    {
      "key": "compileall._SupportsSearch",
      "abstract": "",
      "serializedNode": {
        "type": "PYTHON_CALL_MEMBER",
        "properties": {
          "member": "_SupportsSearch"
        },
        "childSets": {
          "object": [
            {
              "type": "PY_IDENTIFIER",
              "properties": {
                "identifier": "compileall"
              },
              "childSets": {}
            }
          ],
          "arguments": [
            {
              "type": "PY_ARG",
              "childSets": {
                "argument": [
                  {
                    "type": "PYTHON_EXPRESSION",
                    "properties": {},
                    "childSets": {
                      "tokens": []
                    }
                  }
                ]
              },
              "properties": {}
            }
          ]
        }
      }
    },
    {
      "key": "compileall.compile_dir",
      "abstract": "Byte-compile all modules in the given directory tree.",
      "serializedNode": {
        "type": "PYTHON_CALL_MEMBER",
        "properties": {
          "member": "compile_dir"
        },
        "childSets": {
          "object": [
            {
              "type": "PY_IDENTIFIER",
              "properties": {
                "identifier": "compileall"
              },
              "childSets": {}
            }
          ],
          "arguments": [
            {
              "type": "PY_ARG",
              "childSets": {
                "argument": [
                  {
                    "type": "PYTHON_EXPRESSION",
                    "properties": {},
                    "childSets": {
                      "tokens": []
                    }
                  }
                ]
              },
              "properties": {}
            }
          ]
        }
      }
    },
    {
      "key": "compileall.compile_file",
      "abstract": "Byte-compile one file.",
      "serializedNode": {
        "type": "PYTHON_CALL_MEMBER",
        "properties": {
          "member": "compile_file"
        },
        "childSets": {
          "object": [
            {
              "type": "PY_IDENTIFIER",
              "properties": {
                "identifier": "compileall"
              },
              "childSets": {}
            }
          ],
          "arguments": [
            {
              "type": "PY_ARG",
              "childSets": {
                "argument": [
                  {
                    "type": "PYTHON_EXPRESSION",
                    "properties": {},
                    "childSets": {
                      "tokens": []
                    }
                  }
                ]
              },
              "properties": {}
            }
          ]
        }
      }
    },
    {
      "key": "compileall.compile_path",
      "abstract": "Byte-compile all module on sys.path.",
      "serializedNode": {
        "type": "PYTHON_CALL_MEMBER",
        "properties": {
          "member": "compile_path"
        },
        "childSets": {
          "object": [
            {
              "type": "PY_IDENTIFIER",
              "properties": {
                "identifier": "compileall"
              },
              "childSets": {}
            }
          ],
          "arguments": [
            {
              "type": "PY_ARG",
              "childSets": {
                "argument": [
                  {
                    "type": "PYTHON_EXPRESSION",
                    "properties": {},
                    "childSets": {
                      "tokens": []
                    }
                  }
                ]
              },
              "properties": {}
            }
          ]
        }
      }
    }
  ]
}