{
  "category": "contextvars",
  "entries": [
    {
      "key": "contextvars.ContextVar",
      "abstract": "",
      "serializedNode": {
        "type": "PYTHON_CALL_MEMBER",
        "properties": {
          "member": "ContextVar"
        },
        "meta": {
          "params": [
            "name"
          ]
        },
        "childSets": {
          "object": [
            {
              "type": "PY_IDENTIFIER",
              "properties": {
                "identifier": "contextvars"
              },
              "childSets": {}
            }
          ],
          "arguments": [
            {
              "type": "PY_ARG",
              "childSets": {
                "argument": [
                  {
                    "type": "PYTHON_EXPRESSION",
                    "properties": {},
                    "childSets": {
                      "tokens": []
                    }
                  }
                ]
              },
              "properties": {}
            }
          ]
        }
      }
    },
    {
      "key": "contextvars.Token",
      "abstract": "",
      "serializedNode": {
        "type": "PYTHON_CALL_MEMBER",
        "properties": {
          "member": "Token"
        },
        "meta": {
          "params": []
        },
        "childSets": {
          "object": [
            {
              "type": "PY_IDENTIFIER",
              "properties": {
                "identifier": "contextvars"
              },
              "childSets": {}
            }
          ],
          "arguments": []
        }
      }
    },
    {
      "key": "contextvars.copy_context",
      "abstract": "",
      "serializedNode": {
        "type": "PYTHON_CALL_MEMBER",
        "properties": {
          "member": "copy_context"
        },
        "meta": {
          "params": []
        },
        "childSets": {
          "object": [
            {
              "type": "PY_IDENTIFIER",
              "properties": {
                "identifier": "contextvars"
              },
              "childSets": {}
            }
          ],
          "arguments": []
        }
      }
    },
    {
      "key": "contextvars.Context",
      "abstract": "",
      "serializedNode": {
        "type": "PYTHON_CALL_MEMBER",
        "properties": {
          "member": "Context"
        },
        "meta": {
          "params": []
        },
        "childSets": {
          "object": [
            {
              "type": "PY_IDENTIFIER",
              "properties": {
                "identifier": "contextvars"
              },
              "childSets": {}
            }
          ],
          "arguments": []
        }
      }
    }
  ]
}