{
  "category": "linecache",
  "entries": [
    {
      "key": "linecache.cache",
      "abstract": "",
      "serializedNode": {
        "type": "PYTHON_MEMBER",
        "properties": {
          "member": "cache"
        },
        "childSets": {
          "object": [
            {
              "type": "PY_IDENTIFIER",
              "properties": {
                "identifier": "linecache"
              },
              "childSets": {}
            }
          ]
        }
      }
    },
    {
      "key": "linecache.getline",
      "abstract": "Get a line for a Python source file from the cache.",
      "serializedNode": {
        "type": "PYTHON_CALL_MEMBER",
        "properties": {
          "member": "getline"
        },
        "meta": {
          "params": [
            "filename",
            "lineno",
            "module_globals"
          ]
        },
        "childSets": {
          "object": [
            {
              "type": "PY_IDENTIFIER",
              "properties": {
                "identifier": "linecache"
              },
              "childSets": {}
            }
          ],
          "arguments": [
            {
              "type": "PY_ARG",
              "childSets": {
                "argument": [
                  {
                    "type": "PYTHON_EXPRESSION",
                    "properties": {},
                    "childSets": {
                      "tokens": []
                    }
                  }
                ]
              },
              "properties": {}
            },
            {
              "type": "PY_ARG",
              "childSets": {
                "argument": [
                  {
                    "type": "PYTHON_EXPRESSION",
                    "properties": {},
                    "childSets": {
                      "tokens": []
                    }
                  }
                ]
              },
              "properties": {}
            }
          ]
        }
      }
    },
    {
      "key": "linecache.clearcache",
      "abstract": "Clear the cache entirely.",
      "serializedNode": {
        "type": "PYTHON_CALL_MEMBER",
        "properties": {
          "member": "clearcache"
        },
        "meta": {
          "params": []
        },
        "childSets": {
          "object": [
            {
              "type": "PY_IDENTIFIER",
              "properties": {
                "identifier": "linecache"
              },
              "childSets": {}
            }
          ],
          "arguments": []
        }
      }
    },
    {
      "key": "linecache.getlines",
      "abstract": "Get the lines for a Python source file from the cache.",
      "serializedNode": {
        "type": "PYTHON_CALL_MEMBER",
        "properties": {
          "member": "getlines"
        },
        "meta": {
          "params": [
            "filename",
            "module_globals"
          ]
        },
        "childSets": {
          "object": [
            {
              "type": "PY_IDENTIFIER",
              "properties": {
                "identifier": "linecache"
              },
              "childSets": {}
            }
          ],
          "arguments": [
            {
              "type": "PY_ARG",
              "childSets": {
                "argument": [
                  {
                    "type": "PYTHON_EXPRESSION",
                    "properties": {},
                    "childSets": {
                      "tokens": []
                    }
                  }
                ]
              },
              "properties": {}
            }
          ]
        }
      }
    },
    {
      "key": "linecache.checkcache",
      "abstract": "Discard cache entries that are out of date.",
      "serializedNode": {
        "type": "PYTHON_CALL_MEMBER",
        "properties": {
          "member": "checkcache"
        },
        "meta": {
          "params": [
            "filename"
          ]
        },
        "childSets": {
          "object": [
            {
              "type": "PY_IDENTIFIER",
              "properties": {
                "identifier": "linecache"
              },
              "childSets": {}
            }
          ],
          "arguments": [
            {
              "type": "PY_ARG",
              "childSets": {
                "argument": [
                  {
                    "type": "PYTHON_EXPRESSION",
                    "properties": {},
                    "childSets": {
                      "tokens": []
                    }
                  }
                ]
              },
              "properties": {}
            }
          ]
        }
      }
    },
    {
      "key": "linecache.updatecache",
      "abstract": "Update a cache entry and return its list of lines.",
      "serializedNode": {
        "type": "PYTHON_CALL_MEMBER",
        "properties": {
          "member": "updatecache"
        },
        "meta": {
          "params": [
            "filename",
            "module_globals"
          ]
        },
        "childSets": {
          "object": [
            {
              "type": "PY_IDENTIFIER",
              "properties": {
                "identifier": "linecache"
              },
              "childSets": {}
            }
          ],
          "arguments": [
            {
              "type": "PY_ARG",
              "childSets": {
                "argument": [
                  {
                    "type": "PYTHON_EXPRESSION",
                    "properties": {},
                    "childSets": {
                      "tokens": []
                    }
                  }
                ]
              },
              "properties": {}
            }
          ]
        }
      }
    },
    {
      "key": "linecache.lazycache",
      "abstract": "Seed the cache for filename with module_globals.",
      "serializedNode": {
        "type": "PYTHON_CALL_MEMBER",
        "properties": {
          "member": "lazycache"
        },
        "meta": {
          "params": [
            "filename",
            "module_globals"
          ]
        },
        "childSets": {
          "object": [
            {
              "type": "PY_IDENTIFIER",
              "properties": {
                "identifier": "linecache"
              },
              "childSets": {}
            }
          ],
          "arguments": [
            {
              "type": "PY_ARG",
              "childSets": {
                "argument": [
                  {
                    "type": "PYTHON_EXPRESSION",
                    "properties": {},
                    "childSets": {
                      "tokens": []
                    }
                  }
                ]
              },
              "properties": {}
            },
            {
              "type": "PY_ARG",
              "childSets": {
                "argument": [
                  {
                    "type": "PYTHON_EXPRESSION",
                    "properties": {},
                    "childSets": {
                      "tokens": []
                    }
                  }
                ]
              },
              "properties": {}
            }
          ]
        }
      }
    }
  ]
}