{
  "category": "pickle",
  "entries": [
    {
      "key": "pickle.HIGHEST_PROTOCOL",
      "abstract": "",
      "serializedNode": {
        "type": "PYTHON_MEMBER",
        "properties": {
          "member": "HIGHEST_PROTOCOL"
        },
        "childSets": {
          "object": [
            {
              "type": "PY_IDENTIFIER",
              "properties": {
                "identifier": "pickle"
              },
              "childSets": {}
            }
          ]
        }
      }
    },
    {
      "key": "pickle.DEFAULT_PROTOCOL",
      "abstract": "",
      "serializedNode": {
        "type": "PYTHON_MEMBER",
        "properties": {
          "member": "DEFAULT_PROTOCOL"
        },
        "childSets": {
          "object": [
            {
              "type": "PY_IDENTIFIER",
              "properties": {
                "identifier": "pickle"
              },
              "childSets": {}
            }
          ]
        }
      }
    },
    {
      "key": "pickle.bytes_types",
      "abstract": "",
      "serializedNode": {
        "type": "PYTHON_MEMBER",
        "properties": {
          "member": "bytes_types"
        },
        "childSets": {
          "object": [
            {
              "type": "PY_IDENTIFIER",
              "properties": {
                "identifier": "pickle"
              },
              "childSets": {}
            }
          ]
        }
      }
    },
    {
      "key": "pickle.PickleBuffer",
      "abstract": "",
      "serializedNode": {
        "type": "PYTHON_CALL_MEMBER",
        "properties": {
          "member": "PickleBuffer"
        },
        "meta": {
          "params": [
            "buffer"
          ]
        },
        "childSets": {
          "object": [
            {
              "type": "PY_IDENTIFIER",
              "properties": {
                "identifier": "pickle"
              },
              "childSets": {}
            }
          ],
          "arguments": [
            {
              "type": "PY_ARG",
              "childSets": {
                "argument": [
                  {
                    "type": "PYTHON_EXPRESSION",
                    "properties": {},
                    "childSets": {
                      "tokens": []
                    }
                  }
                ]
              },
              "properties": {}
            }
          ]
        }
      }
    },
    {
      "key": "pickle.dump",
      "abstract": "",
      "serializedNode": {
        "type": "PYTHON_CALL_MEMBER",
        "properties": {
          "member": "dump"
        },
        "meta": {
          "params": [
            "obj",
            "file",
            "protocol"
          ]
        },
        "childSets": {
          "object": [
            {
              "type": "PY_IDENTIFIER",
              "properties": {
                "identifier": "pickle"
              },
              "childSets": {}
            }
          ],
          "arguments": [
            {
              "type": "PY_ARG",
              "childSets": {
                "argument": [
                  {
                    "type": "PYTHON_EXPRESSION",
                    "properties": {},
                    "childSets": {
                      "tokens": []
                    }
                  }
                ]
              },
              "properties": {}
            },
            {
              "type": "PY_ARG",
              "childSets": {
                "argument": [
                  {
                    "type": "PYTHON_EXPRESSION",
                    "properties": {},
                    "childSets": {
                      "tokens": []
                    }
                  }
                ]
              },
              "properties": {}
            }
          ]
        }
      }
    },
    {
      "key": "pickle.dumps",
      "abstract": "",
      "serializedNode": {
        "type": "PYTHON_CALL_MEMBER",
        "properties": {
          "member": "dumps"
        },
        "meta": {
          "params": [
            "obj",
            "protocol"
          ]
        },
        "childSets": {
          "object": [
            {
              "type": "PY_IDENTIFIER",
              "properties": {
                "identifier": "pickle"
              },
              "childSets": {}
            }
          ],
          "arguments": [
            {
              "type": "PY_ARG",
              "childSets": {
                "argument": [
                  {
                    "type": "PYTHON_EXPRESSION",
                    "properties": {},
                    "childSets": {
                      "tokens": []
                    }
                  }
                ]
              },
              "properties": {}
            }
          ]
        }
      }
    },
    {
      "key": "pickle.load",
      "abstract": "",
      "serializedNode": {
        "type": "PYTHON_CALL_MEMBER",
        "properties": {
          "member": "load"
        },
        "meta": {
          "params": [
            "file"
          ]
        },
        "childSets": {
          "object": [
            {
              "type": "PY_IDENTIFIER",
              "properties": {
                "identifier": "pickle"
              },
              "childSets": {}
            }
          ],
          "arguments": [
            {
              "type": "PY_ARG",
              "childSets": {
                "argument": [
                  {
                    "type": "PYTHON_EXPRESSION",
                    "properties": {},
                    "childSets": {
                      "tokens": []
                    }
                  }
                ]
              },
              "properties": {}
            }
          ]
        }
      }
    },
    {
      "key": "pickle.loads",
      "abstract": "",
      "serializedNode": {
        "type": "PYTHON_CALL_MEMBER",
        "properties": {
          "member": "loads"
        },
        "meta": {
          "params": [
            "__data"
          ]
        },
        "childSets": {
          "object": [
            {
              "type": "PY_IDENTIFIER",
              "properties": {
                "identifier": "pickle"
              },
              "childSets": {}
            }
          ],
          "arguments": [
            {
              "type": "PY_ARG",
              "childSets": {
                "argument": [
                  {
                    "type": "PYTHON_EXPRESSION",
                    "properties": {},
                    "childSets": {
                      "tokens": []
                    }
                  }
                ]
              },
              "properties": {}
            }
          ]
        }
      }
    },
    {
      "key": "pickle.PickleError",
      "abstract": "A common base class for the other pickling exceptions.",
      "serializedNode": {
        "type": "PYTHON_CALL_MEMBER",
        "properties": {
          "member": "PickleError"
        },
        "meta": {
          "params": []
        },
        "childSets": {
          "object": [
            {
              "type": "PY_IDENTIFIER",
              "properties": {
                "identifier": "pickle"
              },
              "childSets": {}
            }
          ],
          "arguments": []
        }
      }
    },
    {
      "key": "pickle.PicklingError",
      "abstract": "This exception is raised when an unpicklable object is passed to the",
      "serializedNode": {
        "type": "PYTHON_CALL_MEMBER",
        "properties": {
          "member": "PicklingError"
        },
        "meta": {
          "params": []
        },
        "childSets": {
          "object": [
            {
              "type": "PY_IDENTIFIER",
              "properties": {
                "identifier": "pickle"
              },
              "childSets": {}
            }
          ],
          "arguments": []
        }
      }
    },
    {
      "key": "pickle.UnpicklingError",
      "abstract": "This exception is raised when there is a problem unpickling an object,",
      "serializedNode": {
        "type": "PYTHON_CALL_MEMBER",
        "properties": {
          "member": "UnpicklingError"
        },
        "meta": {
          "params": []
        },
        "childSets": {
          "object": [
            {
              "type": "PY_IDENTIFIER",
              "properties": {
                "identifier": "pickle"
              },
              "childSets": {}
            }
          ],
          "arguments": []
        }
      }
    },
    {
      "key": "pickle.Pickler",
      "abstract": "",
      "serializedNode": {
        "type": "PYTHON_CALL_MEMBER",
        "properties": {
          "member": "Pickler"
        },
        "meta": {
          "params": [
            "file",
            "protocol"
          ]
        },
        "childSets": {
          "object": [
            {
              "type": "PY_IDENTIFIER",
              "properties": {
                "identifier": "pickle"
              },
              "childSets": {}
            }
          ],
          "arguments": [
            {
              "type": "PY_ARG",
              "childSets": {
                "argument": [
                  {
                    "type": "PYTHON_EXPRESSION",
                    "properties": {},
                    "childSets": {
                      "tokens": []
                    }
                  }
                ]
              },
              "properties": {}
            }
          ]
        }
      }
    },
    {
      "key": "pickle.Unpickler",
      "abstract": "",
      "serializedNode": {
        "type": "PYTHON_CALL_MEMBER",
        "properties": {
          "member": "Unpickler"
        },
        "meta": {
          "params": [
            "file"
          ]
        },
        "childSets": {
          "object": [
            {
              "type": "PY_IDENTIFIER",
              "properties": {
                "identifier": "pickle"
              },
              "childSets": {}
            }
          ],
          "arguments": [
            {
              "type": "PY_ARG",
              "childSets": {
                "argument": [
                  {
                    "type": "PYTHON_EXPRESSION",
                    "properties": {},
                    "childSets": {
                      "tokens": []
                    }
                  }
                ]
              },
              "properties": {}
            }
          ]
        }
      }
    },
    {
      "key": "pickle.MARK",
      "abstract": "",
      "serializedNode": {
        "type": "PYTHON_MEMBER",
        "properties": {
          "member": "MARK"
        },
        "childSets": {
          "object": [
            {
              "type": "PY_IDENTIFIER",
              "properties": {
                "identifier": "pickle"
              },
              "childSets": {}
            }
          ]
        }
      }
    },
    {
      "key": "pickle.STOP",
      "abstract": "",
      "serializedNode": {
        "type": "PYTHON_MEMBER",
        "properties": {
          "member": "STOP"
        },
        "childSets": {
          "object": [
            {
              "type": "PY_IDENTIFIER",
              "properties": {
                "identifier": "pickle"
              },
              "childSets": {}
            }
          ]
        }
      }
    },
    {
      "key": "pickle.POP",
      "abstract": "",
      "serializedNode": {
        "type": "PYTHON_MEMBER",
        "properties": {
          "member": "POP"
        },
        "childSets": {
          "object": [
            {
              "type": "PY_IDENTIFIER",
              "properties": {
                "identifier": "pickle"
              },
              "childSets": {}
            }
          ]
        }
      }
    },
    {
      "key": "pickle.POP_MARK",
      "abstract": "",
      "serializedNode": {
        "type": "PYTHON_MEMBER",
        "properties": {
          "member": "POP_MARK"
        },
        "childSets": {
          "object": [
            {
              "type": "PY_IDENTIFIER",
              "properties": {
                "identifier": "pickle"
              },
              "childSets": {}
            }
          ]
        }
      }
    },
    {
      "key": "pickle.DUP",
      "abstract": "",
      "serializedNode": {
        "type": "PYTHON_MEMBER",
        "properties": {
          "member": "DUP"
        },
        "childSets": {
          "object": [
            {
              "type": "PY_IDENTIFIER",
              "properties": {
                "identifier": "pickle"
              },
              "childSets": {}
            }
          ]
        }
      }
    },
    {
      "key": "pickle.FLOAT",
      "abstract": "",
      "serializedNode": {
        "type": "PYTHON_MEMBER",
        "properties": {
          "member": "FLOAT"
        },
        "childSets": {
          "object": [
            {
              "type": "PY_IDENTIFIER",
              "properties": {
                "identifier": "pickle"
              },
              "childSets": {}
            }
          ]
        }
      }
    },
    {
      "key": "pickle.INT",
      "abstract": "",
      "serializedNode": {
        "type": "PYTHON_MEMBER",
        "properties": {
          "member": "INT"
        },
        "childSets": {
          "object": [
            {
              "type": "PY_IDENTIFIER",
              "properties": {
                "identifier": "pickle"
              },
              "childSets": {}
            }
          ]
        }
      }
    },
    {
      "key": "pickle.BININT",
      "abstract": "",
      "serializedNode": {
        "type": "PYTHON_MEMBER",
        "properties": {
          "member": "BININT"
        },
        "childSets": {
          "object": [
            {
              "type": "PY_IDENTIFIER",
              "properties": {
                "identifier": "pickle"
              },
              "childSets": {}
            }
          ]
        }
      }
    },
    {
      "key": "pickle.BININT1",
      "abstract": "",
      "serializedNode": {
        "type": "PYTHON_MEMBER",
        "properties": {
          "member": "BININT1"
        },
        "childSets": {
          "object": [
            {
              "type": "PY_IDENTIFIER",
              "properties": {
                "identifier": "pickle"
              },
              "childSets": {}
            }
          ]
        }
      }
    },
    {
      "key": "pickle.LONG",
      "abstract": "",
      "serializedNode": {
        "type": "PYTHON_MEMBER",
        "properties": {
          "member": "LONG"
        },
        "childSets": {
          "object": [
            {
              "type": "PY_IDENTIFIER",
              "properties": {
                "identifier": "pickle"
              },
              "childSets": {}
            }
          ]
        }
      }
    },
    {
      "key": "pickle.BININT2",
      "abstract": "",
      "serializedNode": {
        "type": "PYTHON_MEMBER",
        "properties": {
          "member": "BININT2"
        },
        "childSets": {
          "object": [
            {
              "type": "PY_IDENTIFIER",
              "properties": {
                "identifier": "pickle"
              },
              "childSets": {}
            }
          ]
        }
      }
    },
    {
      "key": "pickle.NONE",
      "abstract": "",
      "serializedNode": {
        "type": "PYTHON_MEMBER",
        "properties": {
          "member": "NONE"
        },
        "childSets": {
          "object": [
            {
              "type": "PY_IDENTIFIER",
              "properties": {
                "identifier": "pickle"
              },
              "childSets": {}
            }
          ]
        }
      }
    },
    {
      "key": "pickle.PERSID",
      "abstract": "",
      "serializedNode": {
        "type": "PYTHON_MEMBER",
        "properties": {
          "member": "PERSID"
        },
        "childSets": {
          "object": [
            {
              "type": "PY_IDENTIFIER",
              "properties": {
                "identifier": "pickle"
              },
              "childSets": {}
            }
          ]
        }
      }
    },
    {
      "key": "pickle.BINPERSID",
      "abstract": "",
      "serializedNode": {
        "type": "PYTHON_MEMBER",
        "properties": {
          "member": "BINPERSID"
        },
        "childSets": {
          "object": [
            {
              "type": "PY_IDENTIFIER",
              "properties": {
                "identifier": "pickle"
              },
              "childSets": {}
            }
          ]
        }
      }
    },
    {
      "key": "pickle.REDUCE",
      "abstract": "",
      "serializedNode": {
        "type": "PYTHON_MEMBER",
        "properties": {
          "member": "REDUCE"
        },
        "childSets": {
          "object": [
            {
              "type": "PY_IDENTIFIER",
              "properties": {
                "identifier": "pickle"
              },
              "childSets": {}
            }
          ]
        }
      }
    },
    {
      "key": "pickle.STRING",
      "abstract": "",
      "serializedNode": {
        "type": "PYTHON_MEMBER",
        "properties": {
          "member": "STRING"
        },
        "childSets": {
          "object": [
            {
              "type": "PY_IDENTIFIER",
              "properties": {
                "identifier": "pickle"
              },
              "childSets": {}
            }
          ]
        }
      }
    },
    {
      "key": "pickle.BINSTRING",
      "abstract": "",
      "serializedNode": {
        "type": "PYTHON_MEMBER",
        "properties": {
          "member": "BINSTRING"
        },
        "childSets": {
          "object": [
            {
              "type": "PY_IDENTIFIER",
              "properties": {
                "identifier": "pickle"
              },
              "childSets": {}
            }
          ]
        }
      }
    },
    {
      "key": "pickle.SHORT_BINSTRING",
      "abstract": "",
      "serializedNode": {
        "type": "PYTHON_MEMBER",
        "properties": {
          "member": "SHORT_BINSTRING"
        },
        "childSets": {
          "object": [
            {
              "type": "PY_IDENTIFIER",
              "properties": {
                "identifier": "pickle"
              },
              "childSets": {}
            }
          ]
        }
      }
    },
    {
      "key": "pickle.UNICODE",
      "abstract": "",
      "serializedNode": {
        "type": "PYTHON_MEMBER",
        "properties": {
          "member": "UNICODE"
        },
        "childSets": {
          "object": [
            {
              "type": "PY_IDENTIFIER",
              "properties": {
                "identifier": "pickle"
              },
              "childSets": {}
            }
          ]
        }
      }
    },
    {
      "key": "pickle.BINUNICODE",
      "abstract": "",
      "serializedNode": {
        "type": "PYTHON_MEMBER",
        "properties": {
          "member": "BINUNICODE"
        },
        "childSets": {
          "object": [
            {
              "type": "PY_IDENTIFIER",
              "properties": {
                "identifier": "pickle"
              },
              "childSets": {}
            }
          ]
        }
      }
    },
    {
      "key": "pickle.APPEND",
      "abstract": "",
      "serializedNode": {
        "type": "PYTHON_MEMBER",
        "properties": {
          "member": "APPEND"
        },
        "childSets": {
          "object": [
            {
              "type": "PY_IDENTIFIER",
              "properties": {
                "identifier": "pickle"
              },
              "childSets": {}
            }
          ]
        }
      }
    },
    {
      "key": "pickle.BUILD",
      "abstract": "",
      "serializedNode": {
        "type": "PYTHON_MEMBER",
        "properties": {
          "member": "BUILD"
        },
        "childSets": {
          "object": [
            {
              "type": "PY_IDENTIFIER",
              "properties": {
                "identifier": "pickle"
              },
              "childSets": {}
            }
          ]
        }
      }
    },
    {
      "key": "pickle.GLOBAL",
      "abstract": "",
      "serializedNode": {
        "type": "PYTHON_MEMBER",
        "properties": {
          "member": "GLOBAL"
        },
        "childSets": {
          "object": [
            {
              "type": "PY_IDENTIFIER",
              "properties": {
                "identifier": "pickle"
              },
              "childSets": {}
            }
          ]
        }
      }
    },
    {
      "key": "pickle.DICT",
      "abstract": "",
      "serializedNode": {
        "type": "PYTHON_MEMBER",
        "properties": {
          "member": "DICT"
        },
        "childSets": {
          "object": [
            {
              "type": "PY_IDENTIFIER",
              "properties": {
                "identifier": "pickle"
              },
              "childSets": {}
            }
          ]
        }
      }
    },
    {
      "key": "pickle.EMPTY_DICT",
      "abstract": "",
      "serializedNode": {
        "type": "PYTHON_MEMBER",
        "properties": {
          "member": "EMPTY_DICT"
        },
        "childSets": {
          "object": [
            {
              "type": "PY_IDENTIFIER",
              "properties": {
                "identifier": "pickle"
              },
              "childSets": {}
            }
          ]
        }
      }
    },
    {
      "key": "pickle.APPENDS",
      "abstract": "",
      "serializedNode": {
        "type": "PYTHON_MEMBER",
        "properties": {
          "member": "APPENDS"
        },
        "childSets": {
          "object": [
            {
              "type": "PY_IDENTIFIER",
              "properties": {
                "identifier": "pickle"
              },
              "childSets": {}
            }
          ]
        }
      }
    },
    {
      "key": "pickle.GET",
      "abstract": "",
      "serializedNode": {
        "type": "PYTHON_MEMBER",
        "properties": {
          "member": "GET"
        },
        "childSets": {
          "object": [
            {
              "type": "PY_IDENTIFIER",
              "properties": {
                "identifier": "pickle"
              },
              "childSets": {}
            }
          ]
        }
      }
    },
    {
      "key": "pickle.BINGET",
      "abstract": "",
      "serializedNode": {
        "type": "PYTHON_MEMBER",
        "properties": {
          "member": "BINGET"
        },
        "childSets": {
          "object": [
            {
              "type": "PY_IDENTIFIER",
              "properties": {
                "identifier": "pickle"
              },
              "childSets": {}
            }
          ]
        }
      }
    },
    {
      "key": "pickle.INST",
      "abstract": "",
      "serializedNode": {
        "type": "PYTHON_MEMBER",
        "properties": {
          "member": "INST"
        },
        "childSets": {
          "object": [
            {
              "type": "PY_IDENTIFIER",
              "properties": {
                "identifier": "pickle"
              },
              "childSets": {}
            }
          ]
        }
      }
    },
    {
      "key": "pickle.LONG_BINGET",
      "abstract": "",
      "serializedNode": {
        "type": "PYTHON_MEMBER",
        "properties": {
          "member": "LONG_BINGET"
        },
        "childSets": {
          "object": [
            {
              "type": "PY_IDENTIFIER",
              "properties": {
                "identifier": "pickle"
              },
              "childSets": {}
            }
          ]
        }
      }
    },
    {
      "key": "pickle.LIST",
      "abstract": "",
      "serializedNode": {
        "type": "PYTHON_MEMBER",
        "properties": {
          "member": "LIST"
        },
        "childSets": {
          "object": [
            {
              "type": "PY_IDENTIFIER",
              "properties": {
                "identifier": "pickle"
              },
              "childSets": {}
            }
          ]
        }
      }
    },
    {
      "key": "pickle.EMPTY_LIST",
      "abstract": "",
      "serializedNode": {
        "type": "PYTHON_MEMBER",
        "properties": {
          "member": "EMPTY_LIST"
        },
        "childSets": {
          "object": [
            {
              "type": "PY_IDENTIFIER",
              "properties": {
                "identifier": "pickle"
              },
              "childSets": {}
            }
          ]
        }
      }
    },
    {
      "key": "pickle.OBJ",
      "abstract": "",
      "serializedNode": {
        "type": "PYTHON_MEMBER",
        "properties": {
          "member": "OBJ"
        },
        "childSets": {
          "object": [
            {
              "type": "PY_IDENTIFIER",
              "properties": {
                "identifier": "pickle"
              },
              "childSets": {}
            }
          ]
        }
      }
    },
    {
      "key": "pickle.PUT",
      "abstract": "",
      "serializedNode": {
        "type": "PYTHON_MEMBER",
        "properties": {
          "member": "PUT"
        },
        "childSets": {
          "object": [
            {
              "type": "PY_IDENTIFIER",
              "properties": {
                "identifier": "pickle"
              },
              "childSets": {}
            }
          ]
        }
      }
    },
    {
      "key": "pickle.BINPUT",
      "abstract": "",
      "serializedNode": {
        "type": "PYTHON_MEMBER",
        "properties": {
          "member": "BINPUT"
        },
        "childSets": {
          "object": [
            {
              "type": "PY_IDENTIFIER",
              "properties": {
                "identifier": "pickle"
              },
              "childSets": {}
            }
          ]
        }
      }
    },
    {
      "key": "pickle.LONG_BINPUT",
      "abstract": "",
      "serializedNode": {
        "type": "PYTHON_MEMBER",
        "properties": {
          "member": "LONG_BINPUT"
        },
        "childSets": {
          "object": [
            {
              "type": "PY_IDENTIFIER",
              "properties": {
                "identifier": "pickle"
              },
              "childSets": {}
            }
          ]
        }
      }
    },
    {
      "key": "pickle.SETITEM",
      "abstract": "",
      "serializedNode": {
        "type": "PYTHON_MEMBER",
        "properties": {
          "member": "SETITEM"
        },
        "childSets": {
          "object": [
            {
              "type": "PY_IDENTIFIER",
              "properties": {
                "identifier": "pickle"
              },
              "childSets": {}
            }
          ]
        }
      }
    },
    {
      "key": "pickle.TUPLE",
      "abstract": "",
      "serializedNode": {
        "type": "PYTHON_MEMBER",
        "properties": {
          "member": "TUPLE"
        },
        "childSets": {
          "object": [
            {
              "type": "PY_IDENTIFIER",
              "properties": {
                "identifier": "pickle"
              },
              "childSets": {}
            }
          ]
        }
      }
    },
    {
      "key": "pickle.EMPTY_TUPLE",
      "abstract": "",
      "serializedNode": {
        "type": "PYTHON_MEMBER",
        "properties": {
          "member": "EMPTY_TUPLE"
        },
        "childSets": {
          "object": [
            {
              "type": "PY_IDENTIFIER",
              "properties": {
                "identifier": "pickle"
              },
              "childSets": {}
            }
          ]
        }
      }
    },
    {
      "key": "pickle.SETITEMS",
      "abstract": "",
      "serializedNode": {
        "type": "PYTHON_MEMBER",
        "properties": {
          "member": "SETITEMS"
        },
        "childSets": {
          "object": [
            {
              "type": "PY_IDENTIFIER",
              "properties": {
                "identifier": "pickle"
              },
              "childSets": {}
            }
          ]
        }
      }
    },
    {
      "key": "pickle.BINFLOAT",
      "abstract": "",
      "serializedNode": {
        "type": "PYTHON_MEMBER",
        "properties": {
          "member": "BINFLOAT"
        },
        "childSets": {
          "object": [
            {
              "type": "PY_IDENTIFIER",
              "properties": {
                "identifier": "pickle"
              },
              "childSets": {}
            }
          ]
        }
      }
    },
    {
      "key": "pickle.TRUE",
      "abstract": "",
      "serializedNode": {
        "type": "PYTHON_MEMBER",
        "properties": {
          "member": "TRUE"
        },
        "childSets": {
          "object": [
            {
              "type": "PY_IDENTIFIER",
              "properties": {
                "identifier": "pickle"
              },
              "childSets": {}
            }
          ]
        }
      }
    },
    {
      "key": "pickle.FALSE",
      "abstract": "",
      "serializedNode": {
        "type": "PYTHON_MEMBER",
        "properties": {
          "member": "FALSE"
        },
        "childSets": {
          "object": [
            {
              "type": "PY_IDENTIFIER",
              "properties": {
                "identifier": "pickle"
              },
              "childSets": {}
            }
          ]
        }
      }
    },
    {
      "key": "pickle.PROTO",
      "abstract": "",
      "serializedNode": {
        "type": "PYTHON_MEMBER",
        "properties": {
          "member": "PROTO"
        },
        "childSets": {
          "object": [
            {
              "type": "PY_IDENTIFIER",
              "properties": {
                "identifier": "pickle"
              },
              "childSets": {}
            }
          ]
        }
      }
    },
    {
      "key": "pickle.NEWOBJ",
      "abstract": "",
      "serializedNode": {
        "type": "PYTHON_MEMBER",
        "properties": {
          "member": "NEWOBJ"
        },
        "childSets": {
          "object": [
            {
              "type": "PY_IDENTIFIER",
              "properties": {
                "identifier": "pickle"
              },
              "childSets": {}
            }
          ]
        }
      }
    },
    {
      "key": "pickle.EXT1",
      "abstract": "",
      "serializedNode": {
        "type": "PYTHON_MEMBER",
        "properties": {
          "member": "EXT1"
        },
        "childSets": {
          "object": [
            {
              "type": "PY_IDENTIFIER",
              "properties": {
                "identifier": "pickle"
              },
              "childSets": {}
            }
          ]
        }
      }
    },
    {
      "key": "pickle.EXT2",
      "abstract": "",
      "serializedNode": {
        "type": "PYTHON_MEMBER",
        "properties": {
          "member": "EXT2"
        },
        "childSets": {
          "object": [
            {
              "type": "PY_IDENTIFIER",
              "properties": {
                "identifier": "pickle"
              },
              "childSets": {}
            }
          ]
        }
      }
    },
    {
      "key": "pickle.EXT4",
      "abstract": "",
      "serializedNode": {
        "type": "PYTHON_MEMBER",
        "properties": {
          "member": "EXT4"
        },
        "childSets": {
          "object": [
            {
              "type": "PY_IDENTIFIER",
              "properties": {
                "identifier": "pickle"
              },
              "childSets": {}
            }
          ]
        }
      }
    },
    {
      "key": "pickle.TUPLE1",
      "abstract": "",
      "serializedNode": {
        "type": "PYTHON_MEMBER",
        "properties": {
          "member": "TUPLE1"
        },
        "childSets": {
          "object": [
            {
              "type": "PY_IDENTIFIER",
              "properties": {
                "identifier": "pickle"
              },
              "childSets": {}
            }
          ]
        }
      }
    },
    {
      "key": "pickle.TUPLE2",
      "abstract": "",
      "serializedNode": {
        "type": "PYTHON_MEMBER",
        "properties": {
          "member": "TUPLE2"
        },
        "childSets": {
          "object": [
            {
              "type": "PY_IDENTIFIER",
              "properties": {
                "identifier": "pickle"
              },
              "childSets": {}
            }
          ]
        }
      }
    },
    {
      "key": "pickle.TUPLE3",
      "abstract": "",
      "serializedNode": {
        "type": "PYTHON_MEMBER",
        "properties": {
          "member": "TUPLE3"
        },
        "childSets": {
          "object": [
            {
              "type": "PY_IDENTIFIER",
              "properties": {
                "identifier": "pickle"
              },
              "childSets": {}
            }
          ]
        }
      }
    },
    {
      "key": "pickle.NEWTRUE",
      "abstract": "",
      "serializedNode": {
        "type": "PYTHON_MEMBER",
        "properties": {
          "member": "NEWTRUE"
        },
        "childSets": {
          "object": [
            {
              "type": "PY_IDENTIFIER",
              "properties": {
                "identifier": "pickle"
              },
              "childSets": {}
            }
          ]
        }
      }
    },
    {
      "key": "pickle.NEWFALSE",
      "abstract": "",
      "serializedNode": {
        "type": "PYTHON_MEMBER",
        "properties": {
          "member": "NEWFALSE"
        },
        "childSets": {
          "object": [
            {
              "type": "PY_IDENTIFIER",
              "properties": {
                "identifier": "pickle"
              },
              "childSets": {}
            }
          ]
        }
      }
    },
    {
      "key": "pickle.LONG1",
      "abstract": "",
      "serializedNode": {
        "type": "PYTHON_MEMBER",
        "properties": {
          "member": "LONG1"
        },
        "childSets": {
          "object": [
            {
              "type": "PY_IDENTIFIER",
              "properties": {
                "identifier": "pickle"
              },
              "childSets": {}
            }
          ]
        }
      }
    },
    {
      "key": "pickle.LONG4",
      "abstract": "",
      "serializedNode": {
        "type": "PYTHON_MEMBER",
        "properties": {
          "member": "LONG4"
        },
        "childSets": {
          "object": [
            {
              "type": "PY_IDENTIFIER",
              "properties": {
                "identifier": "pickle"
              },
              "childSets": {}
            }
          ]
        }
      }
    },
    {
      "key": "pickle.BINBYTES",
      "abstract": "",
      "serializedNode": {
        "type": "PYTHON_MEMBER",
        "properties": {
          "member": "BINBYTES"
        },
        "childSets": {
          "object": [
            {
              "type": "PY_IDENTIFIER",
              "properties": {
                "identifier": "pickle"
              },
              "childSets": {}
            }
          ]
        }
      }
    },
    {
      "key": "pickle.SHORT_BINBYTES",
      "abstract": "",
      "serializedNode": {
        "type": "PYTHON_MEMBER",
        "properties": {
          "member": "SHORT_BINBYTES"
        },
        "childSets": {
          "object": [
            {
              "type": "PY_IDENTIFIER",
              "properties": {
                "identifier": "pickle"
              },
              "childSets": {}
            }
          ]
        }
      }
    },
    {
      "key": "pickle.SHORT_BINUNICODE",
      "abstract": "",
      "serializedNode": {
        "type": "PYTHON_MEMBER",
        "properties": {
          "member": "SHORT_BINUNICODE"
        },
        "childSets": {
          "object": [
            {
              "type": "PY_IDENTIFIER",
              "properties": {
                "identifier": "pickle"
              },
              "childSets": {}
            }
          ]
        }
      }
    },
    {
      "key": "pickle.BINUNICODE8",
      "abstract": "",
      "serializedNode": {
        "type": "PYTHON_MEMBER",
        "properties": {
          "member": "BINUNICODE8"
        },
        "childSets": {
          "object": [
            {
              "type": "PY_IDENTIFIER",
              "properties": {
                "identifier": "pickle"
              },
              "childSets": {}
            }
          ]
        }
      }
    },
    {
      "key": "pickle.BINBYTES8",
      "abstract": "",
      "serializedNode": {
        "type": "PYTHON_MEMBER",
        "properties": {
          "member": "BINBYTES8"
        },
        "childSets": {
          "object": [
            {
              "type": "PY_IDENTIFIER",
              "properties": {
                "identifier": "pickle"
              },
              "childSets": {}
            }
          ]
        }
      }
    },
    {
      "key": "pickle.EMPTY_SET",
      "abstract": "",
      "serializedNode": {
        "type": "PYTHON_MEMBER",
        "properties": {
          "member": "EMPTY_SET"
        },
        "childSets": {
          "object": [
            {
              "type": "PY_IDENTIFIER",
              "properties": {
                "identifier": "pickle"
              },
              "childSets": {}
            }
          ]
        }
      }
    },
    {
      "key": "pickle.ADDITEMS",
      "abstract": "",
      "serializedNode": {
        "type": "PYTHON_MEMBER",
        "properties": {
          "member": "ADDITEMS"
        },
        "childSets": {
          "object": [
            {
              "type": "PY_IDENTIFIER",
              "properties": {
                "identifier": "pickle"
              },
              "childSets": {}
            }
          ]
        }
      }
    },
    {
      "key": "pickle.FROZENSET",
      "abstract": "",
      "serializedNode": {
        "type": "PYTHON_MEMBER",
        "properties": {
          "member": "FROZENSET"
        },
        "childSets": {
          "object": [
            {
              "type": "PY_IDENTIFIER",
              "properties": {
                "identifier": "pickle"
              },
              "childSets": {}
            }
          ]
        }
      }
    },
    {
      "key": "pickle.NEWOBJ_EX",
      "abstract": "",
      "serializedNode": {
        "type": "PYTHON_MEMBER",
        "properties": {
          "member": "NEWOBJ_EX"
        },
        "childSets": {
          "object": [
            {
              "type": "PY_IDENTIFIER",
              "properties": {
                "identifier": "pickle"
              },
              "childSets": {}
            }
          ]
        }
      }
    },
    {
      "key": "pickle.STACK_GLOBAL",
      "abstract": "",
      "serializedNode": {
        "type": "PYTHON_MEMBER",
        "properties": {
          "member": "STACK_GLOBAL"
        },
        "childSets": {
          "object": [
            {
              "type": "PY_IDENTIFIER",
              "properties": {
                "identifier": "pickle"
              },
              "childSets": {}
            }
          ]
        }
      }
    },
    {
      "key": "pickle.MEMOIZE",
      "abstract": "",
      "serializedNode": {
        "type": "PYTHON_MEMBER",
        "properties": {
          "member": "MEMOIZE"
        },
        "childSets": {
          "object": [
            {
              "type": "PY_IDENTIFIER",
              "properties": {
                "identifier": "pickle"
              },
              "childSets": {}
            }
          ]
        }
      }
    },
    {
      "key": "pickle.FRAME",
      "abstract": "",
      "serializedNode": {
        "type": "PYTHON_MEMBER",
        "properties": {
          "member": "FRAME"
        },
        "childSets": {
          "object": [
            {
              "type": "PY_IDENTIFIER",
              "properties": {
                "identifier": "pickle"
              },
              "childSets": {}
            }
          ]
        }
      }
    },
    {
      "key": "pickle.BYTEARRAY8",
      "abstract": "",
      "serializedNode": {
        "type": "PYTHON_MEMBER",
        "properties": {
          "member": "BYTEARRAY8"
        },
        "childSets": {
          "object": [
            {
              "type": "PY_IDENTIFIER",
              "properties": {
                "identifier": "pickle"
              },
              "childSets": {}
            }
          ]
        }
      }
    },
    {
      "key": "pickle.NEXT_BUFFER",
      "abstract": "",
      "serializedNode": {
        "type": "PYTHON_MEMBER",
        "properties": {
          "member": "NEXT_BUFFER"
        },
        "childSets": {
          "object": [
            {
              "type": "PY_IDENTIFIER",
              "properties": {
                "identifier": "pickle"
              },
              "childSets": {}
            }
          ]
        }
      }
    },
    {
      "key": "pickle.READONLY_BUFFER",
      "abstract": "",
      "serializedNode": {
        "type": "PYTHON_MEMBER",
        "properties": {
          "member": "READONLY_BUFFER"
        },
        "childSets": {
          "object": [
            {
              "type": "PY_IDENTIFIER",
              "properties": {
                "identifier": "pickle"
              },
              "childSets": {}
            }
          ]
        }
      }
    },
    {
      "key": "pickle.encode_long",
      "abstract": "Encode a long to a two's complement little-endian binary string.",
      "serializedNode": {
        "type": "PYTHON_CALL_MEMBER",
        "properties": {
          "member": "encode_long"
        },
        "meta": {
          "params": [
            "x"
          ]
        },
        "childSets": {
          "object": [
            {
              "type": "PY_IDENTIFIER",
              "properties": {
                "identifier": "pickle"
              },
              "childSets": {}
            }
          ],
          "arguments": [
            {
              "type": "PY_ARG",
              "childSets": {
                "argument": [
                  {
                    "type": "PYTHON_EXPRESSION",
                    "properties": {},
                    "childSets": {
                      "tokens": []
                    }
                  }
                ]
              },
              "properties": {}
            }
          ]
        }
      }
    },
    {
      "key": "pickle.decode_long",
      "abstract": "Decode a long from a two's complement little-endian binary string.",
      "serializedNode": {
        "type": "PYTHON_CALL_MEMBER",
        "properties": {
          "member": "decode_long"
        },
        "meta": {
          "params": [
            "data"
          ]
        },
        "childSets": {
          "object": [
            {
              "type": "PY_IDENTIFIER",
              "properties": {
                "identifier": "pickle"
              },
              "childSets": {}
            }
          ],
          "arguments": [
            {
              "type": "PY_ARG",
              "childSets": {
                "argument": [
                  {
                    "type": "PYTHON_EXPRESSION",
                    "properties": {},
                    "childSets": {
                      "tokens": []
                    }
                  }
                ]
              },
              "properties": {}
            }
          ]
        }
      }
    }
  ]
}