{
  "category": "runpy",
  "entries": [
    {
      "key": "runpy.run_module",
      "abstract": "Abstract for runpy.run_module",
      "serializedNode": {
        "type": "PYTHON_CALL_MEMBER",
        "childSets": {
          "object": [
            {
              "type": "PY_IDENTIFIER",
              "properties": {
                "identifier": "runpy"
              },
              "childSets": {}
            }
          ],
          "arguments": [
            {
              "type": "PY_ARG",
              "childSets": {
                "argument": [
                  {
                    "type": "PYTHON_EXPRESSION",
                    "properties": {},
                    "childSets": {
                      "tokens": []
                    }
                  }
                ]
              },
              "properties": {}
            }
          ]
        },
        "properties": {
          "member": "run_module"
        }
      }
    },
    {
      "key": "runpy.run_path",
      "abstract": "Abstract for runpy.run_path",
      "serializedNode": {
        "type": "PYTHON_CALL_MEMBER",
        "childSets": {
          "object": [
            {
              "type": "PY_IDENTIFIER",
              "properties": {
                "identifier": "runpy"
              },
              "childSets": {}
            }
          ],
          "arguments": [
            {
              "type": "PY_ARG",
              "childSets": {
                "argument": [
                  {
                    "type": "PYTHON_EXPRESSION",
                    "properties": {},
                    "childSets": {
                      "tokens": []
                    }
                  }
                ]
              },
              "properties": {}
            }
          ]
        },
        "properties": {
          "member": "run_path"
        }
      }
    }
  ]
}