{
  "category": "zoneinfo",
  "entries": [
    {
      "key": "zoneinfo.reset_tzpath",
      "abstract": "Abstract for zoneinfo.reset_tzpath",
      "serializedNode": {
        "type": "PYTHON_CALL_MEMBER",
        "childSets": {
          "object": [
            {
              "type": "PY_IDENTIFIER",
              "properties": {
                "identifier": "zoneinfo"
              },
              "childSets": {}
            }
          ],
          "arguments": [
            {
              "type": "PY_ARG",
              "childSets": {
                "argument": [
                  {
                    "type": "PYTHON_EXPRESSION",
                    "properties": {},
                    "childSets": {
                      "tokens": []
                    }
                  }
                ]
              },
              "properties": {}
            }
          ]
        },
        "properties": {
          "member": "reset_tzpath"
        }
      }
    },
    {
      "key": "zoneinfo.available_timezones",
      "abstract": "Abstract for zoneinfo.available_timezones",
      "serializedNode": {
        "type": "PYTHON_CALL_MEMBER",
        "childSets": {
          "object": [
            {
              "type": "PY_IDENTIFIER",
              "properties": {
                "identifier": "zoneinfo"
              },
              "childSets": {}
            }
          ],
          "arguments": [
            {
              "type": "PY_ARG",
              "childSets": {
                "argument": [
                  {
                    "type": "PYTHON_EXPRESSION",
                    "properties": {},
                    "childSets": {
                      "tokens": []
                    }
                  }
                ]
              },
              "properties": {}
            }
          ]
        },
        "properties": {
          "member": "available_timezones"
        }
      }
    }
  ]
}